langextract_mcp/__init__.py
langextract_mcp/inference.py
langextract_mcp/server.py
langextract_mcp/resources/README.md
langextract_mcp/resources/__init__.py
langextract_mcp/resources/supported-models.md
iflow_mcp_langextract_mcp-0.1.1.dist-info/METADATA
iflow_mcp_langextract_mcp-0.1.1.dist-info/WHEEL
iflow_mcp_langextract_mcp-0.1.1.dist-info/entry_points.txt
iflow_mcp_langextract_mcp-0.1.1.dist-info/licenses/LICENSE
iflow_mcp_langextract_mcp-0.1.1.dist-info/RECORD
