Metadata-Version: 2.4
Name: iflow-mcp_langextract-mcp
Version: 0.1.1
Summary: FastMCP server for Google's langextract library - extract structured information from unstructured text using LLMs
Project-URL: Homepage, https://github.com/your-org/langextract-mcp
Project-URL: Repository, https://github.com/your-org/langextract-mcp
Project-URL: Documentation, https://github.com/your-org/langextract-mcp/blob/main/README.md
Project-URL: Issues, https://github.com/your-org/langextract-mcp/issues
Author: Larsen Weigle
License: Apache-2.0
License-File: LICENSE
Keywords: ai,fastmcp,langextract,llm,mcp,nlp,text-extraction
Classifier: Development Status :: 3 - Alpha
Classifier: Intended Audience :: Developers
Classifier: License :: OSI Approved :: Apache Software License
Classifier: Programming Language :: Python :: 3
Classifier: Programming Language :: Python :: 3.10
Classifier: Programming Language :: Python :: 3.11
Classifier: Programming Language :: Python :: 3.12
Classifier: Topic :: Scientific/Engineering :: Artificial Intelligence
Classifier: Topic :: Software Development :: Libraries :: Python Modules
Classifier: Topic :: Text Processing :: Linguistic
Requires-Python: >=3.10
Requires-Dist: fastmcp>=0.1.0
Requires-Dist: httpx>=0.25.0
Requires-Dist: langextract>=0.1.0
Requires-Dist: openai>=1.0.0
Requires-Dist: pydantic>=2.0.0
Requires-Dist: python-dotenv>=1.0.0
Provides-Extra: dev
Requires-Dist: black>=23.0.0; extra == 'dev'
Requires-Dist: isort>=5.12.0; extra == 'dev'
Requires-Dist: mypy>=1.5.0; extra == 'dev'
Requires-Dist: pre-commit>=3.0.0; extra == 'dev'
Requires-Dist: pytest-asyncio>=0.21.0; extra == 'dev'
Requires-Dist: pytest>=7.0.0; extra == 'dev'
